Metadata-Version: 2.1
Name: pondslider
Version: 0.4.2
Summary: Multipurpose sensor handler, read sensor & do somethings (send, save, trigger, ...) with the value.
Home-page: https://github.com/UedaTakeyuki/pondslider
Author: Takeyuki UEDA
Author-email: gde00107@nifty.com
License: MIT
Keywords: sensor,IoT
Platform: UNKNOWN
Classifier: Development Status :: 4 - Beta
Classifier: Programming Language :: Python
Classifier: Topic :: Terminals
